peopledata_did/__init__.py
peopledata_did/definition.py
peopledata_did/patched_protocols/__init__.py
peopledata_did/patched_protocols/issue_credential/__init__.py
peopledata_did/patched_protocols/issue_credential/definition.py
peopledata_did/patched_protocols/issue_credential/v1_0/__init__.py
peopledata_did/patched_protocols/issue_credential/v1_0/handlers/__init__.py
peopledata_did/patched_protocols/issue_credential/v1_0/handlers/credential_ack_handler.py
peopledata_did/patched_protocols/issue_credential/v1_0/handlers/credential_issue_handler.py
peopledata_did/patched_protocols/issue_credential/v1_0/handlers/credential_offer_handler.py
peopledata_did/patched_protocols/issue_credential/v1_0/handlers/credential_proposal_handler.py
peopledata_did/patched_protocols/issue_credential/v1_0/handlers/credential_request_handler.py
peopledata_did/patched_protocols/issue_credential/v1_0/manager.py
peopledata_did/patched_protocols/issue_credential/v1_0/message_types.py
peopledata_did/patched_protocols/issue_credential/v1_0/messages/__init__.py
peopledata_did/patched_protocols/issue_credential/v1_0/messages/credential_ack.py
peopledata_did/patched_protocols/issue_credential/v1_0/messages/credential_issue.py
peopledata_did/patched_protocols/issue_credential/v1_0/messages/credential_offer.py
peopledata_did/patched_protocols/issue_credential/v1_0/messages/credential_proposal.py
peopledata_did/patched_protocols/issue_credential/v1_0/messages/credential_request.py
peopledata_did/patched_protocols/issue_credential/v1_0/messages/inner/__init__.py
peopledata_did/patched_protocols/issue_credential/v1_0/messages/inner/credential_preview.py
peopledata_did/patched_protocols/issue_credential/v1_0/models/__init__.py
peopledata_did/patched_protocols/issue_credential/v1_0/models/credential_exchange.py
peopledata_did/patched_protocols/issue_credential/v1_0/routes.py
peopledata_did/patched_protocols/present_proof/__init__.py
peopledata_did/patched_protocols/present_proof/definition.py
acapy_peopledata_did-0.1.0.dist-info/LICENSE
acapy_peopledata_did-0.1.0.dist-info/WHEEL
acapy_peopledata_did-0.1.0.dist-info/METADATA
acapy_peopledata_did-0.1.0.dist-info/RECORD
