Metadata-Version: 2.1
Name: acapy-peopledata-did
Version: 0.1.0
Summary: ACA-Py plugin for MyData DID DIDComm protcol
Home-page: https://github.com/decentralised-dataexchange/acapy-mydata-did-protocol
License: License :: OSI Approved :: Apache Software License
Keywords: acapy,aries,peopledata,ssi
Author: jerry zhang
Author-email: jerry.zhang.bill@gmail.com
Requires-Python: >=3.8,<4.0
Classifier: License :: Other/Proprietary License
Classifier: Programming Language :: Python :: 3
Classifier: Programming Language :: Python :: 3.8
Classifier: Programming Language :: Python :: 3.9
Classifier: Programming Language :: Python :: 3.10
Classifier: Topic :: Software Development :: Build Tools
Classifier: Topic :: Software Development :: Libraries :: Python Modules
Requires-Dist: MarkupSafe (==2.0.1)
Requires-Dist: PyJWT (>=2.4.0,<3.0.0)
Requires-Dist: acapy-patched (==0.5.6.dev1)
Requires-Dist: dexa-sdk (==0.1.9)
Requires-Dist: py-multibase (>=1.0.3,<2.0.0)
Requires-Dist: py-solc-x (>=1.1.1,<2.0.0)
Requires-Dist: python3-indy (>=1.16.0,<2.0.0)
Requires-Dist: semver (>=2.13.0,<3.0.0)
Requires-Dist: validators (>=0.20.0,<0.21.0)
Project-URL: Repository, https://github.com/decentralised-dataexchange/acapy-mydata-did-protocol
